ex_tools/__init__.py
ex_tools/exceptions.py
ex_tools/globals.py
ex_tools/functools/__init__.py
ex_tools/functools/defer.py
ex_tools/functools/pipe.py
ex_tools/functools/x_object.py
ex_tools/itertools/__init__.py
ex_tools/itertools/exceptions.py
ex_tools/itertools/functions.py
ex_tools-0.2.0.dist-info/LICENSE
ex_tools-0.2.0.dist-info/METADATA
ex_tools-0.2.0.dist-info/WHEEL
ex_tools-0.2.0.dist-info/top_level.txt
ex_tools-0.2.0.dist-info/RECORD
