Metadata-Version: 2.1
Name: ex-tools
Version: 0.2.0
Summary: Tools that include/extend functools/itertools +alpha
Home-page: https://github.com/yu-ichiro/ex-tools
Author: Yuichiro Luke Smith
Author-email: yuichiro.luke@gmail.com
License: MIT
Platform: UNKNOWN
